MANIFEST.in
Pipfile
README.md
requirements.txt
setup.py
proxy_factory/__init__.py
proxy_factory/factory.py
proxy_factory/proxy_site_spider.py
proxy_factory/settings.py
proxy_factory/utils.py
proxy_factory.egg-info/PKG-INFO
proxy_factory.egg-info/SOURCES.txt
proxy_factory.egg-info/dependency_links.txt
proxy_factory.egg-info/entry_points.txt
proxy_factory.egg-info/requires.txt
proxy_factory.egg-info/top_level.txt
proxy_factory.egg-info/zip-safe