Metadata-Version: 2.1
Name: proxy-factory
Version: 0.3.2
Summary: provide anonymous proxies. 
Home-page: https://www.github.com/ShichaoMa/proxy_factory
Author: cn
Author-email: cnaafhvk@foxmail.com
License: MIT
Keywords: anonymous proxies proxy
Platform: UNKNOWN
Classifier: License :: OSI Approved :: MIT License
Classifier: Programming Language :: Python :: 3
Classifier: Intended Audience :: Developers
Classifier: Operating System :: Unix
